dependably_me/__init__.py
dependably_me/cli/__init__.py
dependably_me/cli/reminders.py
dependably_me/cli/twilio.py
dependably_me/contacts.py
dependably_me/project.py
dependably_me/reminders.py
dependably_me/twilio.py
dependably_me-0.1.0.dist-info/entry_points.txt
dependably_me-0.1.0.dist-info/WHEEL
dependably_me-0.1.0.dist-info/METADATA
dependably_me-0.1.0.dist-info/RECORD
