Metadata-Version: 2.1
Name: dependably-me
Version: 0.1.0
Summary: 
Author: Ken Payne
Author-email: me@kenpayne.co.uk
Requires-Python: >=3.8,<4.0
Classifier: Programming Language :: Python :: 3
Classifier: Programming Language :: Python :: 3.8
Classifier: Programming Language :: Python :: 3.9
Classifier: Programming Language :: Python :: 3.10
Requires-Dist: croniter (>=1.3.7,<2.0.0)
Requires-Dist: humanize (>=4.3.0,<5.0.0)
Requires-Dist: pydantic-yaml[ruamel] (>=0.8.0,<0.9.0)
Requires-Dist: python-dotenv (>=0.21.0,<0.22.0)
Requires-Dist: twilio (>=7.13.0,<8.0.0)
Requires-Dist: typer[all] (>=0.6.1,<0.7.0)
Requires-Dist: tzlocal (>=4.2,<5.0)
